{"stem":"resid","instances":[{"docUri":"search.html","score":3,"contexts":[{"form":"residence","weight":"1","pos":360,"context":"...University. In 1999 he was an artist in <mark>residence<\/mark> at Videopool and Urban Shaman in Winnipeg, where...","fid":"ssDesc3"},{"form":"residence","weight":"1","pos":370,"context":"...Glass.  In 2012 he was an artist in <mark>residence<\/mark> at Villa K. Magdalena in Hamburg, Germany,...","fid":"ssDesc3"},{"form":"resides","weight":"1","pos":424,"context":"...member of Little Pine First Nation, and currently <mark>resides<\/mark> in Toronto.","fid":"ssDesc3"}]}]}