{"stem":"01","instances":[{"docUri":"people.html","score":2,"contexts":[{"form":"01","weight":"1","pos":13816,"context":"...-for-intersectional-and-inclusive-movement\/2017\/<mark>01<\/mark>\/21\/99d888b2-dffd-...","fid":"primary-bio"},{"form":"01","weight":"1","pos":14448,"context":"....com\/magazine\/2016\/08\/<mark>01<\/mark>\/the-trans-community-of-christopher-street\"...","fid":"primary-bio"}]},{"docUri":"person\/person-PERS_000504.html","score":2,"contexts":[{"form":"01","weight":"1","pos":324,"context":"...-for-intersectional-and-inclusive-movement\/2017\/<mark>01<\/mark>\/21\/99d888b2-dffd-...","fid":"primary-bio"},{"form":"01","weight":"1","pos":956,"context":"....com\/magazine\/2016\/08\/<mark>01<\/mark>\/the-trans-community-of-christopher-street\"...","fid":"primary-bio"}]}]}