{"stem":"17","instances":[{"docUri":"people.html","score":2,"contexts":[{"form":"17","weight":"1","pos":2604,"context":"....silashoward.com\/?page_id=<mark>17<\/mark>\"&gt;television&lt;\/a&gt;&lt;\/em&gt;&amp;nbsp;– never straying...","fid":"primary-bio"},{"form":"17","weight":"1","pos":4350,"context":"..., film and music studies. He graduated at <mark>17<\/mark> and went on to perform in high-profile...","fid":"primary-bio"}]},{"docUri":"person\/person-PERS_000034.html","score":1,"contexts":[{"form":"17","weight":"1","pos":190,"context":"....silashoward.com\/?page_id=<mark>17<\/mark>\"&gt;television&lt;\/a&gt;&lt;\/em&gt;&amp;nbsp;– never straying...","fid":"primary-bio"}]},{"docUri":"person\/person-PERS_000062.html","score":1,"contexts":[{"form":"17","weight":"1","pos":161,"context":"..., film and music studies. He graduated at <mark>17<\/mark> and went on to perform in high-profile...","fid":"primary-bio"}]}]}