{"stem":"afro","instances":[{"docUri":"people.html","score":2,"contexts":[{"form":"Afro","weight":"1","pos":13217,"context":"...The Female Menudo, black fag, and the <mark>Afro<\/mark> Sisters -- have left an indelible mark on the...","fid":"primary-bio"},{"form":"Afro","weight":"1","pos":17633,"context":"...community organizing with The Verses Festival of Words, <mark>Afro<\/mark> Van Connect, The Richmond Public Library and the...","fid":"primary-bio"}]},{"docUri":"person\/person-PERS_000498.html","score":1,"contexts":[{"form":"Afro","weight":"1","pos":44,"context":"...The Female Menudo, black fag, and the <mark>Afro<\/mark> Sisters -- have left an indelible mark on the...","fid":"primary-bio"}]},{"docUri":"person\/person-PERS_000567.html","score":1,"contexts":[{"form":"Afro","weight":"1","pos":267,"context":"...community organizing with The Verses Festival of Words, <mark>Afro<\/mark> Van Connect, The Richmond Public Library and the...","fid":"primary-bio"}]}]}