{"stem":"banff","instances":[{"docUri":"people.html","score":1,"contexts":[{"form":"Banff","weight":"1","pos":10589,"context":"...Nội). Lê has presented his work at The <mark>Banff<\/mark> Centre, Alberta, Canada; UCLA Hammer Museum...","fid":"primary-bio"}]},{"docUri":"person\/person-PERS_000188.html","score":1,"contexts":[{"form":"Banff","weight":"1","pos":87,"context":"...Nội). Lê has presented his work at The <mark>Banff<\/mark> Centre, Alberta, Canada; UCLA Hammer Museum...","fid":"primary-bio"}]}]}