{"stem":"brio","instances":[{"docUri":"people.html","score":1,"contexts":[{"form":"BRIO","weight":"1","pos":7188,"context":"...awarded a residency with The Laundromat Project, the <mark>BRIO<\/mark> Award and 1 of the 8 Exciting Filmmakers Shaking...","fid":"primary-bio"}]},{"docUri":"person\/person-PERS_000132.html","score":1,"contexts":[{"form":"BRIO","weight":"1","pos":53,"context":"...awarded a residency with The Laundromat Project, the <mark>BRIO<\/mark> Award and 1 of the 8 Exciting Filmmakers Shaking...","fid":"primary-bio"}]}]}