{"stem":"carl","instances":[{"docUri":"people.html","score":2,"contexts":[{"form":"Carl","weight":"2","pos":12248,"context":"...:       Gwen Haworth  Citation:       Kylar Broadus  Citation:       <mark>Carl<\/mark> Madgett  Citation:       Louis Mitchell  Citation:       Nicholas Rashad...","fid":"name"}]},{"docUri":"person\/person-PERS_000336.html","score":2,"contexts":[{"form":"Carl","weight":"2","pos":5,"context":"                                     Support Trans Artists               <mark>Carl<\/mark> Madgett Birth Year:  Job Title:   Citation:...","fid":"name"}]}]}