{"stem":"consuela","instances":[{"docUri":"media\/media-WORK_000366.html","score":2,"contexts":[{"form":"Consuela","weight":"1","pos":38,"context":"...Mirror, Mirror&lt;\/em&gt;, portrays Hispanic transsexual <mark>Consuela<\/mark> Cosmetic, living with AIDS in NYC and negotiating...","fid":"primary-desc"},{"form":"Consuela","weight":"1","pos":75,"context":"...by mirroring gender through performing it. Surviving grim adversity <mark>Consuela<\/mark> emerges as a powerful spokesperson for her choices and...","fid":"primary-desc"}]}]}