{"stem":"davina","instances":[{"docUri":"people.html","score":2,"contexts":[{"form":"Davina","weight":"2","pos":16037,"context":"...Professor at Brock University.&amp;nbsp;&lt;\/p&gt;\\r\\n Citation:       <mark>Davina<\/mark> Hader  Citation:       Nicci Farrel &lt;p&gt;In 1991 Nicci Farrel...","fid":"name"}]},{"docUri":"person\/person-PERS_000540.html","score":2,"contexts":[{"form":"Davina","weight":"2","pos":5,"context":"                                     Support Trans Artists               <mark>Davina<\/mark> Hader Birth Year:  Job Title: filmmaker|...","fid":"name"}]}]}