{"stem":"dian","instances":[{"docUri":"media\/media-WORK_000036.html","score":3,"contexts":[{"form":"Diane","weight":"2","pos":20,"context":".... Learn more about the TMP                                      Support Trans Artists            <mark>Diane<\/mark> From The Moon Released in  Media Type:  &lt;p&gt;...","fid":"title"},{"form":"Diane","weight":"1","pos":28,"context":"...Type:  &lt;p&gt;Shortly after a hurtful breakup, <mark>Diane<\/mark>, a transgender pagan priestess, finds refuge in...","fid":"primary-desc"}]},{"docUri":"people.html","score":2,"contexts":[{"form":"Diane","weight":"2","pos":5527,"context":"...:       Brit Fryer  Citation:       Sage Yockelson  Citation:       <mark>Diane<\/mark> Elizabeth Castellanos  Citation:       Dina Boyer  Citation:       Zachary...","fid":"name"}]},{"docUri":"person\/person-PERS_000088.html","score":2,"contexts":[{"form":"Diane","weight":"2","pos":5,"context":"                                     Support Trans Artists               <mark>Diane<\/mark> Elizabeth Castellanos Birth Year:  Job Title:   Citation...","fid":"name"}]},{"docUri":"media\/media-WORK_000266.html","score":1,"contexts":[{"form":"Diane","weight":"1","pos":39,"context":"...announced he was pregnant with his trans woman partner <mark>Diane<\/mark> Rodriguez in Ecuador last year. This film is...","fid":"primary-desc"}]}]}