{"stem":"dr","instances":[{"docUri":"people.html","score":4,"contexts":[{"form":"Dr","weight":"1","pos":2014,"context":"...in Toronto. Citation:       Joshua M. Ferguson &lt;p&gt;<mark>Dr<\/mark>. Joshua M. Ferguson (Ph.D) is a...","fid":"primary-bio"},{"form":"Dr","weight":"1","pos":6149,"context":"...a hard plastic surface for identification and love.\" <mark>Dr<\/mark>. Jay Prosser 2015 Citation:       Ivan Coyote Ivan...","fid":"primary-bio"},{"form":"Dr","weight":"1","pos":15872,"context":"..._000277|REFR_000278      Spy Dénommé-Welch &lt;p&gt;<mark>Dr<\/mark>. Spy Dénommé-Welch is a composer, producer,...","fid":"primary-bio"},{"form":"Dr","weight":"1","pos":16092,"context":"...\/hartp\/\" target=\"_blank\"&gt;&lt;em&gt;<mark>Dr<\/mark> Phoebe Hart&lt;\/em&gt;&lt;\/a&gt;&lt;em&gt;&amp;nbsp;is...","fid":"primary-bio"}]},{"docUri":"media\/media-WORK_000363.html","score":2,"contexts":[{"form":"Dr","weight":"1","pos":33,"context":"...documentary on the work of sex-change specialist <mark>Dr<\/mark>. Leo Wollman, including interviews with Dr....","fid":"primary-desc"},{"form":"Dr","weight":"1","pos":38,"context":"...specialist Dr. Leo Wollman, including interviews with <mark>Dr<\/mark>. Wollman and a few of his patients with...","fid":"primary-desc"}]},{"docUri":"media\/media-WORK_000286.html","score":2,"contexts":[{"form":"Dr","weight":"1","pos":80,"context":"...of courage and authenticity. The film also features <mark>Dr<\/mark>. Chris Cochrane and Dr. Esta Porter,...","fid":"primary-desc"},{"form":"Dr","weight":"1","pos":83,"context":"...The film also features Dr. Chris Cochrane and <mark>Dr<\/mark>. Esta Porter, two medical professionals based in...","fid":"primary-desc"}]},{"docUri":"person\/person-PERS_000032.html","score":1,"contexts":[{"form":"Dr","weight":"1","pos":16,"context":"...|author|advocate|artist|producer &lt;p&gt;<mark>Dr<\/mark>. Joshua M. Ferguson (Ph.D) is a...","fid":"primary-bio"}]},{"docUri":"person\/person-PERS_000539.html","score":1,"contexts":[{"form":"Dr","weight":"1","pos":14,"context":"...Job Title: composer|producer|playwright &lt;p&gt;<mark>Dr<\/mark>. Spy Dénommé-Welch is a composer, producer,...","fid":"primary-bio"}]},{"docUri":"person\/person-PERS_000543.html","score":1,"contexts":[{"form":"Dr","weight":"1","pos":25,"context":"...\/hartp\/\" target=\"_blank\"&gt;&lt;em&gt;<mark>Dr<\/mark> Phoebe Hart&lt;\/em&gt;&lt;\/a&gt;&lt;em&gt;&amp;nbsp;is...","fid":"primary-bio"}]},{"docUri":"person\/person-PERS_000113.html","score":1,"contexts":[{"form":"Dr","weight":"1","pos":142,"context":"...a hard plastic surface for identification and love.\" <mark>Dr<\/mark>. Jay Prosser 2015 Citation:                                   Join our mailing...","fid":"primary-bio"}]},{"docUri":"media\/media-WORK_000356.html","score":1,"contexts":[{"form":"Dr","weight":"1","pos":37,"context":"...Gay Time TV, BBC, presents a jocular <mark>Dr<\/mark>. Stanley Biber who performs about 50% of...","fid":"primary-desc"}]}]}