{"stem":"dsm","instances":[{"docUri":"media\/media-WORK_000229.html","score":2,"contexts":[{"form":"DSM","weight":"1","pos":35,"context":"...the Diagnostic and Statistical Manual of Mental Disorders (<mark>DSM<\/mark>)? Historically, doctors and psychiatrists have positioned themselves...","fid":"primary-desc"},{"form":"DSM","weight":"1","pos":104,"context":"...timely, as the 5th edition of the <mark>DSM<\/mark> is scheduled for publication by the American Psychiatric Association...","fid":"primary-desc"}]}]}