{"stem":"dup","instances":[{"docUri":"people.html","score":2,"contexts":[{"form":"DUP","weight":"2","pos":12227,"context":"...Prince  Citation:       Rikki Swin  Citation:       Rikki Swin <mark>DUP<\/mark> OLD  Citation:       Steve Keller  Citation:       Ari Kane...","fid":"name"}]},{"docUri":"person\/person-PERS_000329.html","score":2,"contexts":[{"form":"DUP","weight":"2","pos":7,"context":"                                     Support Trans Artists               Rikki Swin <mark>DUP<\/mark> OLD Birth Year:  Job Title:   Citation:...","fid":"name"}]}]}