{"stem":"guadalajara","instances":[{"docUri":"people.html","score":1,"contexts":[{"form":"Guadalajara","weight":"1","pos":3798,"context":"...2020) and Visitor’s Day (AFI Docs, <mark>Guadalajara<\/mark> Int’l Film Festival, PBS World). Additional producing...","fid":"primary-bio"}]},{"docUri":"person\/person-PERS_000059.html","score":1,"contexts":[{"form":"Guadalajara","weight":"1","pos":118,"context":"...2020) and Visitor’s Day (AFI Docs, <mark>Guadalajara<\/mark> Int’l Film Festival, PBS World). Additional producing...","fid":"primary-bio"}]}]}