{"stem":"gymnasium","instances":[{"docUri":"people.html","score":1,"contexts":[{"form":"Gymnasium","weight":"1","pos":10925,"context":"...:       Tim Lienhard After graduating from the Ellenrieder-<mark>Gymnasium<\/mark> in Konstanz in 1979 , he studied at the...","fid":"primary-bio"}]},{"docUri":"person\/person-PERS_000189.html","score":1,"contexts":[{"form":"Gymnasium","weight":"1","pos":15,"context":"...Title: director After graduating from the Ellenrieder-<mark>Gymnasium<\/mark> in Konstanz in 1979 , he studied at the...","fid":"primary-bio"}]}]}