{"stem":"im","instances":[{"docUri":"people.html","score":1,"contexts":[{"form":"im","weight":"1","pos":15125,"context":"...selling book &lt;a href=\"\/projects\/writing\/<mark>im<\/mark>-afraid-of-men\"&gt;&lt;cite&gt;I'm&amp;...","fid":"primary-bio"}]},{"docUri":"person\/person-PERS_000534.html","score":1,"contexts":[{"form":"im","weight":"1","pos":36,"context":"...selling book &lt;a href=\"\/projects\/writing\/<mark>im<\/mark>-afraid-of-men\"&gt;&lt;cite&gt;I'm&amp;...","fid":"primary-bio"}]}]}