{"stem":"intergener","instances":[{"docUri":"people.html","score":1,"contexts":[{"form":"intergenerational","weight":"1","pos":10347,"context":"...and artistic director of Pioneer Winter Collective, an <mark>intergenerational<\/mark> and physically integrated dance-theater company, rooted...","fid":"primary-bio"}]},{"docUri":"person\/person-PERS_000187.html","score":1,"contexts":[{"form":"intergenerational","weight":"1","pos":24,"context":"...and artistic director of Pioneer Winter Collective, an <mark>intergenerational<\/mark> and physically integrated dance-theater company, rooted...","fid":"primary-bio"}]}]}