{"stem":"janet-mock-interviews-salma-hayek","instances":[{"docUri":"people.html","score":1,"contexts":[{"form":"janet-mock-interviews-salma-hayek","weight":"1","pos":14112,"context":"...msnbc.com\/so-popular\/watch\/<mark>janet-mock-interviews-salma-hayek<\/mark>-532486724002\" rel=\"noopener\" target=\"_blank\"...","fid":"primary-bio"}]},{"docUri":"person\/person-PERS_000504.html","score":1,"contexts":[{"form":"janet-mock-interviews-salma-hayek","weight":"1","pos":620,"context":"...msnbc.com\/so-popular\/watch\/<mark>janet-mock-interviews-salma-hayek<\/mark>-532486724002\" rel=\"noopener\" target=\"_blank\"...","fid":"primary-bio"}]}]}