{"stem":"jürgen","instances":[{"docUri":"people.html","score":2,"contexts":[{"form":"Jürgen","weight":"2","pos":13022,"context":"...:       Doris Wishman  Citation:       Lars Drinkrow  Citation:       <mark>Jürgen<\/mark> Uren  Citation:       Baillie Walsh  Citation:       Faraz Ahmed...","fid":"name"}]},{"docUri":"person\/person-PERS_000444.html","score":2,"contexts":[{"form":"Jürgen","weight":"2","pos":5,"context":"                                     Support Trans Artists               <mark>Jürgen<\/mark> Uren Birth Year:  Job Title:   Citation:...","fid":"name"}]}]}