{"stem":"lucia","instances":[{"docUri":"people.html","score":2,"contexts":[{"form":"Lucia","weight":"2","pos":353,"context":"...San Francisco Media Archive.&amp;nbsp;&lt;\/p&gt;\\r\\n Citation:       <mark>Lucia<\/mark> Davis  Citation:       Susana Aikin &lt;p&gt;Susana Aikin is...","fid":"name"}]},{"docUri":"person\/person-PERS_000007.html","score":2,"contexts":[{"form":"Lucia","weight":"2","pos":5,"context":"                                     Support Trans Artists               <mark>Lucia<\/mark> Davis Birth Year:  Job Title:   Citation:...","fid":"name"}]},{"docUri":"media\/media-WORK_000220.html","score":1,"contexts":[{"form":"Lucia","weight":"1","pos":151,"context":"...-breaking narrative possibilities. First-time director <mark>Lucia<\/mark> Puenzo handles the film's difficult subject matter with grace...","fid":"primary-desc"}]}]}