{"stem":"mortal","instances":[{"docUri":"media\/media-WORK_000375.html","score":1,"contexts":[{"form":"mortal","weight":"1","pos":36,"context":"...story of a disillusioned angel who decides to become <mark>mortal<\/mark> and upon reaching earth seeks the companionship of a...","fid":"primary-desc"}]},{"docUri":"media\/media-WORK_000431.html","score":1,"contexts":[{"form":"mortality","weight":"1","pos":165,"context":"...a grim cancer diagnosis, Kate confronts her own <mark>mortality<\/mark> and purpose in life, giving her own motto...","fid":"primary-desc"}]}]}