{"stem":"nalac","instances":[{"docUri":"people.html","score":1,"contexts":[{"form":"NALAC","weight":"1","pos":9041,"context":"...by The San Francisco Arts Commission, Sundance, <mark>NALAC<\/mark> (National Association of Latino Arts and Cultures),...","fid":"primary-bio"}]},{"docUri":"person\/person-PERS_000169.html","score":1,"contexts":[{"form":"NALAC","weight":"1","pos":74,"context":"...by The San Francisco Arts Commission, Sundance, <mark>NALAC<\/mark> (National Association of Latino Arts and Cultures),...","fid":"primary-bio"}]}]}