{"stem":"overcom","instances":[{"docUri":"media\/media-WORK_000191.html","score":1,"contexts":[{"form":"overcome","weight":"1","pos":95,"context":"...a glimpse into a tight knit community that has <mark>overcome<\/mark> great obstacles to find the freedom to be true...","fid":"primary-desc"}]},{"docUri":"media\/media-WORK_000049.html","score":1,"contexts":[{"form":"overcomes","weight":"1","pos":36,"context":"...-like creature enduring a tormented birth, who <mark>overcomes<\/mark> bondage from a world not made for them. The...","fid":"primary-desc"}]}]}