{"stem":"phoeb","instances":[{"docUri":"people.html","score":3,"contexts":[{"form":"Phoebe","weight":"2","pos":16079,"context":"....&amp;nbsp;&lt;\/p&gt;\\r\\n Citation:       Lisset Barcellos  Citation:       <mark>Phoebe<\/mark> Hart &lt;p&gt;&lt;a href=\"http:\/\/staff.qut...","fid":"name"},{"form":"Phoebe","weight":"1","pos":16093,"context":"...hartp\/\" target=\"_blank\"&gt;&lt;em&gt;Dr <mark>Phoebe<\/mark> Hart&lt;\/em&gt;&lt;\/a&gt;&lt;em&gt;&amp;nbsp;is an...","fid":"primary-bio"}]},{"docUri":"person\/person-PERS_000543.html","score":3,"contexts":[{"form":"Phoebe","weight":"2","pos":5,"context":"                                     Support Trans Artists               <mark>Phoebe<\/mark> Hart Birth Year:  Job Title: filmmaker|...","fid":"name"},{"form":"Phoebe","weight":"1","pos":26,"context":"...hartp\/\" target=\"_blank\"&gt;&lt;em&gt;Dr <mark>Phoebe<\/mark> Hart&lt;\/em&gt;&lt;\/a&gt;&lt;em&gt;&amp;nbsp;is an...","fid":"primary-bio"}]},{"docUri":"media\/media-WORK_000454.html","score":2,"contexts":[{"form":"Phoebe","weight":"1","pos":29,"context":"...in 2011 Media Type:  &lt;p&gt;Documentary filmmaker, <mark>Phoebe<\/mark> Hart, comes clean on her journey of self...","fid":"primary-desc"},{"form":"Phoebe","weight":"1","pos":52,"context":"...mother's outright refusal to be in the film, <mark>Phoebe<\/mark> decides she must push on with her quest to...","fid":"primary-desc"}]}]}