{"stem":"port","instances":[{"docUri":"people.html","score":2,"contexts":[{"form":"Portes","weight":"2","pos":11690,"context":"...Ian Polk  Citation:       Michael Barrett  Citation:       Gil <mark>Portes<\/mark>  Citation:       Karen Nobes  Citation:       James Diamond &lt;p&gt;...","fid":"name"}]},{"docUri":"person\/person-PERS_000216.html","score":2,"contexts":[{"form":"Portes","weight":"2","pos":6,"context":"                                     Support Trans Artists               Gil <mark>Portes<\/mark> Birth Year:  Job Title:   Citation:                                   Join...","fid":"name"}]}]}