{"stem":"revel","instances":[{"docUri":"media\/media-WORK_000411.html","score":1,"contexts":[{"form":"revelation","weight":"1","pos":92,"context":"..., it becomes a moment of tender, triumphant <mark>revelation<\/mark>.'&lt;\/em&gt; (Andy Medhurts, Sight &amp;...","fid":"primary-desc"}]},{"docUri":"media\/media-WORK_000388.html","score":1,"contexts":[{"form":"revelation","weight":"1","pos":52,"context":"...discover that Alexina is not a woman. The <mark>revelation<\/mark> shocks Alexina, but not her lover, who...","fid":"primary-desc"}]},{"docUri":"media\/media-WORK_000431.html","score":1,"contexts":[{"form":"revelations","weight":"1","pos":84,"context":"...em&gt;captures rollicking public performances and painful personal <mark>revelations<\/mark> bearing witness to the pioneering gender outlaw who inhabits...","fid":"primary-desc"}]}]}