{"stem":"selv","instances":[{"docUri":"people.html","score":1,"contexts":[{"form":"Selves","weight":"1","pos":7933,"context":"...the forthcoming 2nd edition of Trans Bodies Trans <mark>Selves<\/mark>. When not eating\/sleeping\/breathing everything...","fid":"primary-bio"}]},{"docUri":"person\/person-PERS_000138.html","score":1,"contexts":[{"form":"Selves","weight":"1","pos":205,"context":"...the forthcoming 2nd edition of Trans Bodies Trans <mark>Selves<\/mark>. When not eating\/sleeping\/breathing everything...","fid":"primary-bio"}]}]}