{"stem":"sunset","instances":[{"docUri":"people.html","score":1,"contexts":[{"form":"Sunset","weight":"1","pos":2644,"context":"...:\/\/www.silashoward.com\/?p=541\"&gt;<mark>Sunset<\/mark> Stories&lt;\/a&gt;&lt;\/em&gt;, premiered at SXSW and was...","fid":"primary-bio"}]},{"docUri":"person\/person-PERS_000034.html","score":1,"contexts":[{"form":"Sunset","weight":"1","pos":230,"context":"...:\/\/www.silashoward.com\/?p=541\"&gt;<mark>Sunset<\/mark> Stories&lt;\/a&gt;&lt;\/em&gt;, premiered at SXSW and was...","fid":"primary-bio"}]}]}