{"stem":"surgic","instances":[{"docUri":"media\/media-WORK_000357.html","score":1,"contexts":[{"form":"surgical","weight":"1","pos":41,"context":"...Hollywood. Kristy has doubts about the final, <mark>surgical<\/mark> solution to her gender-quest but transexually is...","fid":"primary-desc"}]},{"docUri":"media\/media-WORK_000422.html","score":1,"contexts":[{"form":"surgical","weight":"1","pos":65,"context":"...a penis' through family and medical crisis and many <mark>surgical<\/mark> interventions to help her become the pure and beautiful...","fid":"primary-desc"}]}]}