{"stem":"sylvia","instances":[{"docUri":"people.html","score":2,"contexts":[{"form":"sylvia","weight":"1","pos":14677,"context":"...-profile-when-janet-mock-talks-about-<mark>sylvia<\/mark>-rivera-on-twitter\/\" rel=\"noopener\" target...","fid":"primary-bio"},{"form":"Sylvia","weight":"1","pos":14684,"context":"...twitter\/\" rel=\"noopener\" target=\"_blank\"&gt;<mark>Sylvia<\/mark> Rivera Law Project&lt;\/a&gt;&amp;nbsp;have all honored Janet...","fid":"primary-bio"}]},{"docUri":"person\/person-PERS_000504.html","score":2,"contexts":[{"form":"sylvia","weight":"1","pos":1185,"context":"...-profile-when-janet-mock-talks-about-<mark>sylvia<\/mark>-rivera-on-twitter\/\" rel=\"noopener\" target...","fid":"primary-bio"},{"form":"Sylvia","weight":"1","pos":1192,"context":"...twitter\/\" rel=\"noopener\" target=\"_blank\"&gt;<mark>Sylvia<\/mark> Rivera Law Project&lt;\/a&gt;&amp;nbsp;have all honored Janet...","fid":"primary-bio"}]},{"docUri":"media\/media-WORK_000174.html","score":1,"contexts":[{"form":"Sylvia","weight":"1","pos":49,"context":"...and transgender civil rights organizers, including Stonewall legend <mark>Sylvia<\/mark> Rivera.&lt;\/p&gt;\\r\\n Citation: REFR_000156                                 Join our...","fid":"primary-desc"}]}]}