{"stem":"threat","instances":[{"docUri":"people.html","score":1,"contexts":[{"form":"Threat","weight":"1","pos":1120,"context":"...2008 Madsen&amp;nbsp;co-founded the <mark>Threat<\/mark> Level Queer Shorts bi-monthly screening series that...","fid":"primary-bio"}]},{"docUri":"person\/person-PERS_000023.html","score":1,"contexts":[{"form":"Threat","weight":"1","pos":197,"context":"...2008 Madsen&amp;nbsp;co-founded the <mark>Threat<\/mark> Level Queer Shorts bi-monthly screening series that...","fid":"primary-bio"}]},{"docUri":"media\/media-WORK_000263.html","score":1,"contexts":[{"form":"threat","weight":"1","pos":40,"context":"...in rural America, where violence is a constant <mark>threat<\/mark> and transition can seem like a refuge. It...","fid":"primary-desc"}]}]}