{"stem":"windsom","instances":[{"docUri":"people.html","score":2,"contexts":[{"form":"Windsome","weight":"2","pos":11862,"context":"...Corrine Bot  Citation:       Annette Kennerley  Citation:       Adelaide <mark>Windsome<\/mark>  Citation:       Wren Warner  Citation:       Alexander Antunes Siqueira...","fid":"name"}]},{"docUri":"person\/person-PERS_000241.html","score":2,"contexts":[{"form":"Windsome","weight":"2","pos":6,"context":"                                     Support Trans Artists               Adelaide <mark>Windsome<\/mark> Birth Year:  Job Title:   Citation:                                   Join...","fid":"name"}]}]}